{"nm":"Main Scene","ddd":0,"h":500,"w":500,"meta":{"g":"@lottiefiles/creator 1.19.0"},"layers":[{"ty":0,"nm":" Main Scene","sr":1,"st":0,"op":60,"ip":0,"hd":false,"ddd":0,"bm":0,"hasMask":false,"ao":0,"ks":{"a":{"a":0,"k":[174.8324155619772,278.13823232827383]},"s":{"a":0,"k":[90,90]},"sk":{"a":0,"k":0},"p":{"a":0,"k":[242,106]},"r":{"a":0,"k":-133},"sa":{"a":0,"k":0},"o":{"a":0,"k":100}},"ef":[],"w":500,"h":500,"refId":"precomp_Main Scene_baa8f0dc-88e3-44d0-8f23-b47b5fefaee8","ind":1},{"ty":0,"nm":" Main Scene","sr":1,"st":0,"op":60,"ip":0,"hd":false,"ddd":0,"bm":0,"hasMask":false,"ao":0,"ks":{"a":{"a":0,"k":[146,292]},"s":{"a":0,"k":[90,90]},"sk":{"a":0,"k":0},"p":{"a":0,"k":[210,350]},"r":{"a":0,"k":46},"sa":{"a":0,"k":0},"o":{"a":0,"k":100}},"ef":[],"w":500,"h":500,"refId":"precomp_Main Scene_baa8f0dc-88e3-44d0-8f23-b47b5fefaee8","ind":2},{"ty":0,"nm":" Main Scene","sr":1,"st":0,"op":60,"ip":0,"hd":false,"ddd":0,"bm":0,"hasMask":false,"ao":0,"ks":{"a":{"a":0,"k":[176.16648708829274,278.0363666350098]},"s":{"a":0,"k":[90,90]},"sk":{"a":0,"k":0},"p":{"a":0,"k":[370,232]},"r":{"a":0,"k":-405},"sa":{"a":0,"k":0},"o":{"a":0,"k":100}},"ef":[],"w":500,"h":500,"refId":"precomp_Main Scene_baa8f0dc-88e3-44d0-8f23-b47b5fefaee8","ind":3},{"ty":0,"nm":" Main Scene","sr":1,"st":0,"op":60,"ip":0,"hd":false,"ddd":0,"bm":0,"hasMask":false,"ao":0,"ks":{"a":{"a":0,"k":[176.16648708829274,278.0363666350098]},"s":{"a":0,"k":[90,90]},"sk":{"a":0,"k":0},"p":{"a":0,"k":[115,242]},"r":{"a":0,"k":132},"sa":{"a":0,"k":0},"o":{"a":0,"k":100}},"ef":[],"w":500,"h":500,"refId":"precomp_Main Scene_baa8f0dc-88e3-44d0-8f23-b47b5fefaee8","ind":4},{"ty":4,"nm":"Ellipse 1","sr":1,"st":11,"op":60,"ip":11,"hd":false,"ddd":0,"bm":0,"hasMask":false,"ao":0,"ks":{"a":{"a":0,"k":[0,0]},"s":{"a":0,"k":[110,110]},"sk":{"a":0,"k":0},"p":{"a":0,"k":[244,234]},"r":{"a":0,"k":0},"sa":{"a":0,"k":0},"o":{"a":1,"k":[{"o":{"x":0.167,"y":0.167},"i":{"x":0.833,"y":0.833},"s":[0],"t":11},{"s":[100],"t":21}]}},"ef":[],"shapes":[{"ty":"el","bm":0,"hd":false,"nm":"Ellipse Path 1","d":1,"p":{"a":0,"k":[0,0]},"s":{"a":0,"k":[45,45]}},{"ty":"fl","bm":0,"hd":false,"nm":"Fill","c":{"a":0,"k":[0.851,0.1333,0.1569]},"r":2,"o":{"a":0,"k":100}}],"ind":5}],"v":"5.7.0","fr":30,"op":60,"ip":0,"assets":[{"nm":"Main Scene_1","id":"precomp_Main Scene_baa8f0dc-88e3-44d0-8f23-b47b5fefaee8","layers":[{"ty":4,"nm":"first","sr":1,"st":0,"op":60,"ip":0,"hd":false,"ddd":0,"bm":0,"hasMask":false,"ao":0,"ks":{"a":{"a":0,"k":[0,0]},"s":{"a":1,"k":[{"o":{"x":0.167,"y":0.167},"i":{"x":0.833,"y":0.833},"s":[15,15],"t":0},{"s":[50,50],"t":12}]},"sk":{"a":0,"k":0},"p":{"a":1,"k":[{"o":{"x":0.167,"y":0.167},"i":{"x":0.833,"y":0.833},"s":[550,280.25],"t":0},{"s":[74,278.0625],"t":12}]},"r":{"a":0,"k":0},"sa":{"a":0,"k":0},"o":{"a":1,"k":[{"o":{"x":0.167,"y":0.167},"i":{"x":0.833,"y":0.833},"s":[0],"t":0},{"s":[100],"t":12}]}},"ef":[],"shapes":[{"ty":"el","bm":0,"hd":false,"nm":"Ellipse Path 13","d":1,"p":{"a":0,"k":[0,0]},"s":{"a":0,"k":[100,100]}},{"ty":"fl","bm":0,"hd":false,"nm":"Fill","c":{"a":0,"k":[0.851,0.1333,0.1569]},"r":2,"o":{"a":0,"k":100}}],"ind":1},{"ty":4,"nm":"second","sr":1,"st":0,"op":60,"ip":0,"hd":false,"ddd":0,"bm":0,"hasMask":false,"ao":0,"ks":{"a":{"a":0,"k":[0,0]},"s":{"a":1,"k":[{"o":{"x":0.167,"y":0.167},"i":{"x":0.833,"y":0.833},"s":[15,15],"t":3},{"s":[50,50],"t":15}]},"sk":{"a":0,"k":0},"p":{"a":1,"k":[{"o":{"x":0.167,"y":0.167},"i":{"x":0.833,"y":0.833},"s":[550,280.25],"t":3},{"s":[175.5,278],"t":15}]},"r":{"a":0,"k":0},"sa":{"a":0,"k":0},"o":{"a":1,"k":[{"o":{"x":0.167,"y":0.167},"i":{"x":0.833,"y":0.833},"s":[0],"t":3},{"s":[100],"t":15}]}},"ef":[],"shapes":[{"ty":"el","bm":0,"hd":false,"nm":"Ellipse Path 13","d":1,"p":{"a":0,"k":[0,0]},"s":{"a":0,"k":[100,100]}},{"ty":"fl","bm":0,"hd":false,"nm":"Fill","c":{"a":0,"k":[0.851,0.1333,0.1569]},"r":2,"o":{"a":0,"k":100}}],"ind":2},{"ty":4,"nm":"third","sr":1,"st":0,"op":60,"ip":0,"hd":false,"ddd":0,"bm":0,"hasMask":false,"ao":0,"ks":{"a":{"a":0,"k":[0,0]},"s":{"a":1,"k":[{"o":{"x":0.167,"y":0.167},"i":{"x":0.833,"y":0.833},"s":[15,15],"t":6},{"s":[50,50],"t":18}]},"sk":{"a":0,"k":0},"p":{"a":1,"k":[{"o":{"x":0.167,"y":0.167},"i":{"x":0.833,"y":0.833},"s":[550,280.25],"t":6},{"s":[277,278.0625],"t":18}]},"r":{"a":0,"k":0},"sa":{"a":0,"k":0},"o":{"a":1,"k":[{"o":{"x":0.167,"y":0.167},"i":{"x":0.833,"y":0.833},"s":[0],"t":6},{"s":[100],"t":18}]}},"ef":[],"shapes":[{"ty":"el","bm":0,"hd":false,"nm":"Ellipse Path 13","d":1,"p":{"a":0,"k":[0,0]},"s":{"a":0,"k":[100,100]}},{"ty":"fl","bm":0,"hd":false,"nm":"Fill","c":{"a":0,"k":[0.851,0.1333,0.1569]},"r":2,"o":{"a":0,"k":100}}],"ind":3}]}]}